easy_console_table/__init__.py
easy_console_table/horizontal_table.py
easy_console_table/table_abc.py
easy_console_table/table_abc_s_entry.py
easy_console_table/table_error.py
easy_console_table/two_entry_table.py
easy_console_table/utils_function.py
easy_console_table/vertical_table.py
easy_console_table-0.1.0.dist-info/LICENCE
easy_console_table-0.1.0.dist-info/METADATA
easy_console_table-0.1.0.dist-info/WHEEL
easy_console_table-0.1.0.dist-info/top_level.txt
easy_console_table-0.1.0.dist-info/RECORD
