Metadata-Version: 2.1
Name: easy-console-table
Version: 0.1.0
Summary: A simple package to easily create a table in console.
Author: flastar
Project-URL: Homepage, https://github.com/flastar-fr/easy_console_table
Classifier: License :: OSI Approved :: MIT License
Classifier: Programming Language :: Python :: 3.10
Classifier: Operating System :: OS Independent
Requires-Python: >=3.10
License-File: LICENCE
